django_extra_views-0.16.0.dist-info/licenses/AUTHORS.rst
django_extra_views-0.16.0.dist-info/licenses/LICENSE
extra_views/__init__.py
extra_views/advanced.py
extra_views/dates.py
extra_views/formsets.py
extra_views/generic.py
extra_views/models.py
extra_views/contrib/__init__.py
extra_views/contrib/mixins.py
django_extra_views-0.16.0.dist-info/METADATA
django_extra_views-0.16.0.dist-info/WHEEL
django_extra_views-0.16.0.dist-info/top_level.txt
django_extra_views-0.16.0.dist-info/RECORD
